helloworld/__init__.py
helloworld/hi.py
helloworld/hiname.py
helloworld_jsnook-0.0.2.dist-info/LICENSE
helloworld_jsnook-0.0.2.dist-info/METADATA
helloworld_jsnook-0.0.2.dist-info/WHEEL
helloworld_jsnook-0.0.2.dist-info/top_level.txt
helloworld_jsnook-0.0.2.dist-info/RECORD
