Metadata-Version: 2.1
Name: helloworld-jsnook
Version: 0.0.2
Summary: Hello world package
Home-page: UNKNOWN
License: UNKNOWN
Platform: UNKNOWN
Classifier: Programming Language :: Python :: 3
Classifier: License :: OSI Approved :: MIT License
Classifier: Operating System :: OS Independent
Requires-Python: >=3.6
